README.md
setup.py
yulk/__init__.py
yulk/__main__.py
yulk/apb.xlsx
yulk/marimo.ipynb
yulk/mydb.db
yulk/setupmo.bat
yulk/skills.txt
yulk/start9855.bat
yulk/tim.py
yulk.egg-info/PKG-INFO
yulk.egg-info/SOURCES.txt
yulk.egg-info/dependency_links.txt
yulk.egg-info/requires.txt
yulk.egg-info/top_level.txt
yulk/cn/readme.txt
yulk/en/readme.txt
yulk/mo/cefr.py
yulk/mo/cekn.py
yulk/mo/clause.py
yulk/mo/damage.py
yulk/mo/dfbar.py
yulk/mo/dfdot.py
yulk/mo/dfplot.py
yulk/mo/dm.py
yulk/mo/ecdic.py
yulk/mo/fts.py
yulk/mo/gram4.py
yulk/mo/hello.py
yulk/mo/hiawl.py
yulk/mo/img-base64.py
yulk/mo/intro.py
yulk/mo/knowledge.py
yulk/mo/lempos.py
yulk/mo/level.py
yulk/mo/model.py
yulk/mo/myinput.py
yulk/mo/myplt.py
yulk/mo/mytest.py
yulk/mo/myu.py
yulk/mo/open.py
yulk/mo/parkv.py
yulk/mo/practice.py
yulk/mo/svo.py
yulk/mo/testinput.py
yulk/mo/testwc.py
yulk/mo/topicwords.py
yulk/mo/txtidf.py
yulk/mo/wordinsnt.py
yulk/mo/wordpy.py
yulk/par/advmodad.parquet
yulk/par/advmodda.parquet
yulk/par/advmoddv.parquet
yulk/par/advmodvd.parquet
yulk/par/amodan.parquet
yulk/par/amodna.parquet
yulk/par/apb.parquet
yulk/par/cefr.parquet
yulk/par/conjvv.parquet
yulk/par/dobjnv.parquet
yulk/par/dobjvn.parquet
yulk/par/lemlex.parquet
yulk/par/lempos.parquet
yulk/par/myu.parquet
yulk/par/nsubjnv.parquet
yulk/par/nsubjvn.parquet
yulk/par/prepvp.parquet
yulk/par/simv.parquet
yulk/par/verbform.parquet
yulk/par/wordmf.parquet
yulk/par/wordpy.parquet
yulk/park/awl.parquet
yulk/park/cet4.parquet
yulk/park/cet6.parquet
yulk/park/gsl1.parquet
yulk/park/gsl2.parquet
yulk/park/negative.parquet
yulk/park/positive.parquet
yulk/park/stop.parquet
yulk/park/wordlist.parquet
yulk/parkv/adjcate.parquet
yulk/parkv/cate.parquet
yulk/parkv/cekn.parquet
yulk/parkv/ecdic.parquet
yulk/parkv/eclist.parquet
yulk/parkv/ed1.parquet
yulk/parkv/framenet.parquet
yulk/parkv/freq.parquet
yulk/parkv/grade.parquet
yulk/parkv/idf.parquet
yulk/parkv/lemlexlist.parquet
yulk/parkv/lemmf.parquet
yulk/parkv/level.parquet
yulk/parkv/lexlem.parquet
yulk/parkv/nouncate.parquet
yulk/parkv/sentiment.parquet
yulk/parkv/synonym.parquet
yulk/parkv/verbcate.parquet
