Metadata-Version: 2.1
Name: yulk
Version: 0.0.35
Summary: yulk
Home-page: https://github.com/
Author: yulk
Author-email: 1918118941@qq.com
Classifier: Programming Language :: Python :: 3
Classifier: License :: OSI Approved :: MIT License
Classifier: Operating System :: OS Independent
Requires-Python: >=3.9
Requires-Dist: spacy>3.8.0
Requires-Dist: marimo
Requires-Dist: altair
Requires-Dist: plotly
Requires-Dist: matplotlib
Requires-Dist: duckdb
Requires-Dist: fire>=0.7.1
Requires-Dist: wget>=3.2
Requires-Dist: whoosh
